[
  {
    "title": "Producto de ejemplo 1",
    "description": "Descripción del producto de ejemplo 1",
    "price": 19.99,
    "code": "ABC123",
    "stock": 10,
    "status": true,
    "category": "Electronics",
    "id": 1
  },
  {
    "title": "Producto de ejemplo 44",
    "description": "Descripción del producto de ejemplo 54",
    "price": 19.99,
    "code": "ABC145h",
    "stock": 10,
    "status": true,
    "category": "Electronics",
    "thumbnails": [],
    "id": 7
  },
  {
    "title": "Producto de ejemplo 444",
    "description": "Descripción del producto de ejemplo 544",
    "price": 19.9,
    "code": "ABC112",
    "stock": 10,
    "status": true,
    "category": "Electronics",
    "thumbnails": [],
    "id": 8
  }
]